proxy_retriever_pyro/__init__.py
proxy_retriever_pyro/main.py
proxy_retriever_pyro-0.0.1.dist-info/METADATA
proxy_retriever_pyro-0.0.1.dist-info/WHEEL
proxy_retriever_pyro-0.0.1.dist-info/licenses/LICENSE
proxy_retriever_pyro-0.0.1.dist-info/RECORD
